columnTypeDetector/__init__.py
columnTypeDetector/main.py
columntypedetector-0.2.4.dist-info/licenses/LICENSE
columntypedetector-0.2.4.dist-info/METADATA
columntypedetector-0.2.4.dist-info/WHEEL
columntypedetector-0.2.4.dist-info/top_level.txt
columntypedetector-0.2.4.dist-info/RECORD
