Metadata-Version: 2.4
Name: columnTypeDetector
Version: 0.2.4
Summary: Detect types of columns in delimited files using DuckDB and pandas
Author: Vikas Bhaskar Vooradi
Author-email: vikasvooradi.developer@gmail.com
License: MIT
Classifier: Programming Language :: Python :: 3
Classifier: Operating System :: OS Independent
Classifier: License :: OSI Approved :: MIT License
Requires-Python: >=3.12.3
License-File: LICENSE
Requires-Dist: duckdb>=1.3.2
Requires-Dist: pandas>=2.1.4
Dynamic: author
Dynamic: author-email
Dynamic: classifier
Dynamic: description
Dynamic: description-content-type
Dynamic: license
Dynamic: license-file
Dynamic: requires-dist
Dynamic: requires-python
Dynamic: summary
